[
    {
        "Node IP": "213.239.234.xxx",
        "Block ID": 2117019,
        "Time Diff": 4.663
    },
    {
        "Node IP": "37.27.68.xxx",
        "Block ID": 2117019,
        "Time Diff": 4.706
    },
    {
        "Node IP": "97.85.41.xxx",
        "Block ID": 2117019,
        "Time Diff": 4.849
    },
    {
        "Node IP": "79.190.201.xxx",
        "Block ID": 2117019,
        "Time Diff": 5.11
    },
    {
        "Node IP": "189.217.92.xxx",
        "Block ID": 2117019,
        "Time Diff": 5.188
    },
    {
        "Node IP": "73.156.3.xxx",
        "Block ID": 2117019,
        "Time Diff": 5.217
    },
    {
        "Node IP": "27.109.214.xxx",
        "Block ID": 2117019,
        "Time Diff": 5.406
    },
    {
        "Node IP": "207.188.7.xxx",
        "Block ID": 2117019,
        "Time Diff": 5.43
    },
    {
        "Node IP": "162.19.99.xxx",
        "Block ID": 2117019,
        "Time Diff": 5.503
    },
    {
        "Node IP": "66.203.113.xxx",
        "Block ID": 2117019,
        "Time Diff": 5.539
    },
    {
        "Node IP": "96.250.163.xxx",
        "Block ID": 2117019,
        "Time Diff": 5.804
    },
    {
        "Node IP": "186.233.185.xxx",
        "Block ID": 2117019,
        "Time Diff": 5.849
    },
    {
        "Node IP": "185.7.170.xxx",
        "Block ID": 2117019,
        "Time Diff": 5.989
    },
    {
        "Node IP": "58.169.131.xxx",
        "Block ID": 2117019,
        "Time Diff": 6.015
    },
    {
        "Node IP": "84.59.129.xxx",
        "Block ID": 2117019,
        "Time Diff": 6.409
    },
    {
        "Node IP": "98.122.100.xxx",
        "Block ID": 2117019,
        "Time Diff": 6.524
    },
    {
        "Node IP": "178.217.199.xxx",
        "Block ID": 2117019,
        "Time Diff": 6.752
    },
    {
        "Node IP": "207.188.7.xxx",
        "Block ID": 2117019,
        "Time Diff": 6.868
    },
    {
        "Node IP": "71.167.199.xxx",
        "Block ID": 2117019,
        "Time Diff": 6.902
    },
    {
        "Node IP": "83.6.123.xxx",
        "Block ID": 2117019,
        "Time Diff": 6.918
    },
    {
        "Node IP": "113.176.163.xxx",
        "Block ID": 2117019,
        "Time Diff": 6.924
    },
    {
        "Node IP": "74.50.76.xxx",
        "Block ID": 2117019,
        "Time Diff": 6.937
    },
    {
        "Node IP": "51.79.19.xxx",
        "Block ID": 2117019,
        "Time Diff": 7.047
    },
    {
        "Node IP": "160.202.130.xxx",
        "Block ID": 2117019,
        "Time Diff": 7.051
    },
    {
        "Node IP": "135.181.246.xxx",
        "Block ID": 2117019,
        "Time Diff": 7.077
    },
    {
        "Node IP": "188.214.130.xxx",
        "Block ID": 2117019,
        "Time Diff": 7.11
    },
    {
        "Node IP": "1.162.196.xxx",
        "Block ID": 2117019,
        "Time Diff": 7.15
    },
    {
        "Node IP": "31.179.130.xxx",
        "Block ID": 2117019,
        "Time Diff": 7.433
    },
    {
        "Node IP": "37.27.61.xxx",
        "Block ID": 2117019,
        "Time Diff": 7.646
    },
    {
        "Node IP": "144.76.3.xxx",
        "Block ID": 2117019,
        "Time Diff": 7.705
    },
    {
        "Node IP": "5.182.87.xxx",
        "Block ID": 2117019,
        "Time Diff": 8.007
    },
    {
        "Node IP": "162.55.2.xxx",
        "Block ID": 2117019,
        "Time Diff": 8.094
    },
    {
        "Node IP": "109.205.213.xxx",
        "Block ID": 2117019,
        "Time Diff": 8.304
    },
    {
        "Node IP": "74.50.77.xxx",
        "Block ID": 2117019,
        "Time Diff": 8.336
    },
    {
        "Node IP": "144.208.193.xxx",
        "Block ID": 2117019,
        "Time Diff": 8.379
    },
    {
        "Node IP": "190.242.27.xxx",
        "Block ID": 2117019,
        "Time Diff": 8.402
    },
    {
        "Node IP": "64.20.46.xxx",
        "Block ID": 2117019,
        "Time Diff": 8.569
    },
    {
        "Node IP": "213.76.115.xxx",
        "Block ID": 2117019,
        "Time Diff": 8.599
    },
    {
        "Node IP": "144.168.61.xxx",
        "Block ID": 2117019,
        "Time Diff": 8.689
    },
    {
        "Node IP": "174.128.251.xxx",
        "Block ID": 2117019,
        "Time Diff": 8.731
    },
    {
        "Node IP": "43.133.227.xxx",
        "Block ID": 2117019,
        "Time Diff": 8.956
    },
    {
        "Node IP": "69.10.38.xxx",
        "Block ID": 2117019,
        "Time Diff": 9.27
    },
    {
        "Node IP": "89.77.74.xxx",
        "Block ID": 2117019,
        "Time Diff": 9.287
    },
    {
        "Node IP": "84.247.185.xxx",
        "Block ID": 2117019,
        "Time Diff": 9.383
    },
    {
        "Node IP": "129.226.81.xxx",
        "Block ID": 2117019,
        "Time Diff": 9.384
    },
    {
        "Node IP": "43.133.70.xxx",
        "Block ID": 2117019,
        "Time Diff": 9.489
    },
    {
        "Node IP": "154.38.162.xxx",
        "Block ID": 2117019,
        "Time Diff": 9.601
    },
    {
        "Node IP": "43.135.22.xxx",
        "Block ID": 2117019,
        "Time Diff": 9.626
    },
    {
        "Node IP": "84.247.168.xxx",
        "Block ID": 2117019,
        "Time Diff": 9.627
    },
    {
        "Node IP": "65.109.67.xxx",
        "Block ID": 2117019,
        "Time Diff": 9.644
    },
    {
        "Xenobi Ranking": 34
    },
    {
        "Last Updated": "2024-03-17T22:02:28.982449"
    }
]