[
    {
        "Node IP": "181.214.147.xxx",
        "Block ID": 3265497,
        "Time Diff": 3.898
    },
    {
        "Node IP": "66.23.234.xxx",
        "Block ID": 3265497,
        "Time Diff": 4.343
    },
    {
        "Node IP": "185.7.170.xxx",
        "Block ID": 3265497,
        "Time Diff": 4.346
    },
    {
        "Node IP": "213.239.234.xxx",
        "Block ID": 3265497,
        "Time Diff": 4.637
    },
    {
        "Node IP": "64.121.75.xxx",
        "Block ID": 3265497,
        "Time Diff": 4.714
    },
    {
        "Node IP": "73.156.3.xxx",
        "Block ID": 3265497,
        "Time Diff": 4.723
    },
    {
        "Node IP": "144.208.193.xxx",
        "Block ID": 3265497,
        "Time Diff": 4.753
    },
    {
        "Node IP": "88.198.54.xxx",
        "Block ID": 3265497,
        "Time Diff": 4.769
    },
    {
        "Node IP": "188.137.48.xxx",
        "Block ID": 3265497,
        "Time Diff": 4.807
    },
    {
        "Node IP": "189.217.80.xxx",
        "Block ID": 3265497,
        "Time Diff": 4.869
    },
    {
        "Node IP": "58.169.131.xxx",
        "Block ID": 3265497,
        "Time Diff": 5.049
    },
    {
        "Node IP": "213.239.194.xxx",
        "Block ID": 3265497,
        "Time Diff": 5.059
    },
    {
        "Node IP": "173.208.193.xxx",
        "Block ID": 3265497,
        "Time Diff": 5.065
    },
    {
        "Node IP": "74.50.77.xxx",
        "Block ID": 3265497,
        "Time Diff": 5.161
    },
    {
        "Node IP": "162.19.99.xxx",
        "Block ID": 3265497,
        "Time Diff": 5.162
    },
    {
        "Node IP": "79.190.201.xxx",
        "Block ID": 3265497,
        "Time Diff": 5.205
    },
    {
        "Node IP": "97.85.41.xxx",
        "Block ID": 3265497,
        "Time Diff": 5.23
    },
    {
        "Node IP": "188.117.156.xxx",
        "Block ID": 3265497,
        "Time Diff": 5.346
    },
    {
        "Node IP": "109.205.213.xxx",
        "Block ID": 3265497,
        "Time Diff": 5.398
    },
    {
        "Node IP": "57.128.95.xxx",
        "Block ID": 3265497,
        "Time Diff": 5.495
    },
    {
        "Node IP": "188.117.173.xxx",
        "Block ID": 3265497,
        "Time Diff": 5.655
    },
    {
        "Node IP": "67.85.107.xxx",
        "Block ID": 3265497,
        "Time Diff": 5.954
    },
    {
        "Node IP": "65.108.134.xxx",
        "Block ID": 3265497,
        "Time Diff": 6.103
    },
    {
        "Node IP": "198.84.243.xxx",
        "Block ID": 3265497,
        "Time Diff": 6.104
    },
    {
        "Node IP": "93.180.190.xxx",
        "Block ID": 3265497,
        "Time Diff": 6.139
    },
    {
        "Node IP": "159.196.169.xxx",
        "Block ID": 3265497,
        "Time Diff": 6.192
    },
    {
        "Node IP": "65.109.112.xxx",
        "Block ID": 3265497,
        "Time Diff": 6.24
    },
    {
        "Node IP": "65.109.114.xxx",
        "Block ID": 3265497,
        "Time Diff": 6.27
    },
    {
        "Node IP": "144.76.3.xxx",
        "Block ID": 3265497,
        "Time Diff": 6.483
    },
    {
        "Node IP": "27.109.214.xxx",
        "Block ID": 3265497,
        "Time Diff": 6.542
    },
    {
        "Node IP": "64.20.45.xxx",
        "Block ID": 3265497,
        "Time Diff": 6.569
    },
    {
        "Node IP": "216.219.86.xxx",
        "Block ID": 3265497,
        "Time Diff": 6.582
    },
    {
        "Node IP": "185.166.169.xxx",
        "Block ID": 3265497,
        "Time Diff": 6.616
    },
    {
        "Node IP": "66.23.236.xxx",
        "Block ID": 3265497,
        "Time Diff": 6.758
    },
    {
        "Node IP": "161.97.146.xxx",
        "Block ID": 3265497,
        "Time Diff": 6.787
    },
    {
        "Node IP": "212.102.58.xxx",
        "Block ID": 3265497,
        "Time Diff": 6.9
    },
    {
        "Node IP": "67.217.54.xxx",
        "Block ID": 3265497,
        "Time Diff": 6.925
    },
    {
        "Node IP": "185.22.10.xxx",
        "Block ID": 3265497,
        "Time Diff": 7.019
    },
    {
        "Node IP": "69.10.51.xxx",
        "Block ID": 3265497,
        "Time Diff": 7.045
    },
    {
        "Node IP": "176.109.50.xxx",
        "Block ID": 3265497,
        "Time Diff": 7.075
    },
    {
        "Node IP": "94.250.201.xxx",
        "Block ID": 3265497,
        "Time Diff": 7.092
    },
    {
        "Node IP": "135.181.246.xxx",
        "Block ID": 3265497,
        "Time Diff": 7.105
    },
    {
        "Node IP": "14.245.215.xxx",
        "Block ID": 3265497,
        "Time Diff": 7.206
    },
    {
        "Node IP": "64.20.33.xxx",
        "Block ID": 3265497,
        "Time Diff": 7.207
    },
    {
        "Node IP": "205.209.114.xxx",
        "Block ID": 3265497,
        "Time Diff": 7.219
    },
    {
        "Node IP": "205.209.110.xxx",
        "Block ID": 3265497,
        "Time Diff": 7.243
    },
    {
        "Node IP": "74.50.76.xxx",
        "Block ID": 3265497,
        "Time Diff": 7.274
    },
    {
        "Node IP": "206.72.207.xxx",
        "Block ID": 3265497,
        "Time Diff": 7.289
    },
    {
        "Node IP": "74.50.75.xxx",
        "Block ID": 3265497,
        "Time Diff": 7.314
    },
    {
        "Node IP": "216.158.226.xxx",
        "Block ID": 3265497,
        "Time Diff": 7.326
    },
    {
        "Xenobi Ranking": 14
    },
    {
        "Last Updated": "2024-05-06T08:15:09.480300"
    }
]