[
    {
        "Node IP": "74.50.78.xxx",
        "Block ID": 3784297,
        "Time Diff": 1.057
    },
    {
        "Node IP": "203.30.15.xxx",
        "Block ID": 3784297,
        "Time Diff": 1.114
    },
    {
        "Node IP": "89.64.42.xxx",
        "Block ID": 3784297,
        "Time Diff": 1.12
    },
    {
        "Node IP": "74.50.75.xxx",
        "Block ID": 3784297,
        "Time Diff": 1.141
    },
    {
        "Node IP": "213.76.115.xxx",
        "Block ID": 3784297,
        "Time Diff": 1.246
    },
    {
        "Node IP": "85.215.99.xxx",
        "Block ID": 3784297,
        "Time Diff": 1.27
    },
    {
        "Node IP": "95.156.246.xxx",
        "Block ID": 3784297,
        "Time Diff": 1.282
    },
    {
        "Node IP": "4.213.182.xxx",
        "Block ID": 3784297,
        "Time Diff": 1.301
    },
    {
        "Node IP": "52.140.99.xxx",
        "Block ID": 3784297,
        "Time Diff": 1.33
    },
    {
        "Node IP": "43.163.243.xxx",
        "Block ID": 3784297,
        "Time Diff": 1.449
    },
    {
        "Node IP": "45.129.180.xxx",
        "Block ID": 3784297,
        "Time Diff": 1.462
    },
    {
        "Node IP": "45.15.157.xxx",
        "Block ID": 3784297,
        "Time Diff": 1.479
    },
    {
        "Node IP": "185.166.169.xxx",
        "Block ID": 3784297,
        "Time Diff": 1.493
    },
    {
        "Node IP": "37.27.108.xxx",
        "Block ID": 3784297,
        "Time Diff": 1.53
    },
    {
        "Node IP": "94.228.169.xxx",
        "Block ID": 3784297,
        "Time Diff": 1.721
    },
    {
        "Node IP": "14.29.121.xxx",
        "Block ID": 3784297,
        "Time Diff": 1.767
    },
    {
        "Node IP": "67.211.215.xxx",
        "Block ID": 3784297,
        "Time Diff": 1.881
    },
    {
        "Node IP": "38.242.209.xxx",
        "Block ID": 3784297,
        "Time Diff": 1.926
    },
    {
        "Node IP": "95.217.32.xxx",
        "Block ID": 3784297,
        "Time Diff": 1.944
    },
    {
        "Node IP": "207.180.254.xxx",
        "Block ID": 3784297,
        "Time Diff": 2.018
    },
    {
        "Node IP": "159.205.161.xxx",
        "Block ID": 3784297,
        "Time Diff": 2.274
    },
    {
        "Node IP": "77.89.123.xxx",
        "Block ID": 3784297,
        "Time Diff": 2.298
    },
    {
        "Node IP": "37.27.51.xxx",
        "Block ID": 3784297,
        "Time Diff": 2.403
    },
    {
        "Node IP": "42.118.16.xxx",
        "Block ID": 3784297,
        "Time Diff": 2.412
    },
    {
        "Node IP": "95.156.230.xxx",
        "Block ID": 3784297,
        "Time Diff": 2.414
    },
    {
        "Node IP": "173.249.26.xxx",
        "Block ID": 3784297,
        "Time Diff": 2.422
    },
    {
        "Node IP": "88.198.54.xxx",
        "Block ID": 3784297,
        "Time Diff": 2.45
    },
    {
        "Node IP": "162.55.2.xxx",
        "Block ID": 3784297,
        "Time Diff": 2.751
    },
    {
        "Node IP": "51.255.74.xxx",
        "Block ID": 3784297,
        "Time Diff": 2.832
    },
    {
        "Node IP": "213.199.46.xxx",
        "Block ID": 3784297,
        "Time Diff": 2.835
    },
    {
        "Node IP": "84.247.133.xxx",
        "Block ID": 3784297,
        "Time Diff": 3.059
    },
    {
        "Node IP": "95.217.61.xxx",
        "Block ID": 3784297,
        "Time Diff": 3.236
    },
    {
        "Node IP": "113.166.212.xxx",
        "Block ID": 3784297,
        "Time Diff": 3.317
    },
    {
        "Node IP": "144.91.66.xxx",
        "Block ID": 3784297,
        "Time Diff": 4.007
    },
    {
        "Node IP": "213.239.194.xxx",
        "Block ID": 3784297,
        "Time Diff": 4.074
    },
    {
        "Node IP": "103.35.64.xxx",
        "Block ID": 3784297,
        "Time Diff": 5.211
    },
    {
        "Node IP": "84.247.182.xxx",
        "Block ID": 3784297,
        "Time Diff": 6.421
    },
    {
        "Node IP": "5.182.86.xxx",
        "Block ID": 3784297,
        "Time Diff": 90.669
    },
    {
        "Node IP": "173.212.213.xxx",
        "Block ID": 3784297,
        "Time Diff": 386.173
    },
    {
        "Node IP": "185.7.170.xxx",
        "Block ID": 3784297,
        "Time Diff": 564.243
    },
    {
        "Node IP": "37.27.68.xxx",
        "Block ID": 3784297,
        "Time Diff": 655.129
    },
    {
        "Node IP": "144.208.193.xxx",
        "Block ID": 3784297,
        "Time Diff": 668.904
    },
    {
        "Node IP": "212.102.58.xxx",
        "Block ID": 3784297,
        "Time Diff": 709.549
    },
    {
        "Node IP": "57.128.95.xxx",
        "Block ID": 3784297,
        "Time Diff": 736.105
    },
    {
        "Node IP": "189.217.80.xxx",
        "Block ID": 3784297,
        "Time Diff": 736.463
    },
    {
        "Node IP": "188.117.173.xxx",
        "Block ID": 3784297,
        "Time Diff": 762.445
    },
    {
        "Node IP": "37.27.61.xxx",
        "Block ID": 3784297,
        "Time Diff": 778.986
    },
    {
        "Node IP": "173.214.170.xxx",
        "Block ID": 3784297,
        "Time Diff": 804.91
    },
    {
        "Node IP": "78.46.80.xxx",
        "Block ID": 3784297,
        "Time Diff": 849.283
    },
    {
        "Node IP": "74.50.76.xxx",
        "Block ID": 3784297,
        "Time Diff": 856.292
    },
    {
        "Last Updated": "2024-07-04T10:48:01.446411"
    }
]