[
    {
        "Node IP": "198.84.243.xxx",
        "Block ID": 3731738,
        "Time Diff": 1.013
    },
    {
        "Node IP": "159.196.168.xxx",
        "Block ID": 3731738,
        "Time Diff": 1.014
    },
    {
        "Node IP": "149.50.108.xxx",
        "Block ID": 3731738,
        "Time Diff": 1.02
    },
    {
        "Node IP": "65.108.134.xxx",
        "Block ID": 3731738,
        "Time Diff": 1.034
    },
    {
        "Node IP": "74.50.75.xxx",
        "Block ID": 3731738,
        "Time Diff": 1.039
    },
    {
        "Node IP": "69.10.38.xxx",
        "Block ID": 3731738,
        "Time Diff": 1.047
    },
    {
        "Node IP": "65.108.68.xxx",
        "Block ID": 3731738,
        "Time Diff": 1.116
    },
    {
        "Node IP": "185.225.232.xxx",
        "Block ID": 3731738,
        "Time Diff": 1.127
    },
    {
        "Node IP": "67.217.61.xxx",
        "Block ID": 3731738,
        "Time Diff": 1.166
    },
    {
        "Node IP": "161.97.162.xxx",
        "Block ID": 3731738,
        "Time Diff": 1.185
    },
    {
        "Node IP": "43.163.243.xxx",
        "Block ID": 3731738,
        "Time Diff": 1.21
    },
    {
        "Node IP": "95.156.246.xxx",
        "Block ID": 3731738,
        "Time Diff": 1.222
    },
    {
        "Node IP": "84.247.185.xxx",
        "Block ID": 3731738,
        "Time Diff": 1.239
    },
    {
        "Node IP": "161.97.144.xxx",
        "Block ID": 3731738,
        "Time Diff": 1.249
    },
    {
        "Node IP": "93.180.190.xxx",
        "Block ID": 3731738,
        "Time Diff": 1.275
    },
    {
        "Node IP": "135.181.246.xxx",
        "Block ID": 3731738,
        "Time Diff": 1.312
    },
    {
        "Node IP": "161.97.130.xxx",
        "Block ID": 3731738,
        "Time Diff": 1.352
    },
    {
        "Node IP": "4.213.182.xxx",
        "Block ID": 3731738,
        "Time Diff": 1.361
    },
    {
        "Node IP": "65.109.52.xxx",
        "Block ID": 3731738,
        "Time Diff": 1.371
    },
    {
        "Node IP": "185.166.169.xxx",
        "Block ID": 3731738,
        "Time Diff": 1.374
    },
    {
        "Node IP": "94.228.169.xxx",
        "Block ID": 3731738,
        "Time Diff": 1.389
    },
    {
        "Node IP": "37.27.108.xxx",
        "Block ID": 3731738,
        "Time Diff": 1.495
    },
    {
        "Node IP": "150.109.196.xxx",
        "Block ID": 3731738,
        "Time Diff": 1.496
    },
    {
        "Node IP": "109.173.196.xxx",
        "Block ID": 3731738,
        "Time Diff": 1.51
    },
    {
        "Node IP": "162.19.99.xxx",
        "Block ID": 3731738,
        "Time Diff": 1.513
    },
    {
        "Node IP": "159.205.161.xxx",
        "Block ID": 3731738,
        "Time Diff": 1.576
    },
    {
        "Node IP": "5.182.86.xxx",
        "Block ID": 3731738,
        "Time Diff": 1.599
    },
    {
        "Node IP": "213.239.194.xxx",
        "Block ID": 3731738,
        "Time Diff": 1.613
    },
    {
        "Node IP": "85.215.99.xxx",
        "Block ID": 3731738,
        "Time Diff": 1.617
    },
    {
        "Node IP": "185.137.21.xxx",
        "Block ID": 3731738,
        "Time Diff": 1.64
    },
    {
        "Node IP": "45.129.180.xxx",
        "Block ID": 3731738,
        "Time Diff": 1.717
    },
    {
        "Node IP": "95.217.32.xxx",
        "Block ID": 3731738,
        "Time Diff": 1.768
    },
    {
        "Node IP": "188.117.169.xxx",
        "Block ID": 3731738,
        "Time Diff": 1.79
    },
    {
        "Node IP": "67.211.215.xxx",
        "Block ID": 3731738,
        "Time Diff": 1.791
    },
    {
        "Node IP": "159.65.183.xxx",
        "Block ID": 3731738,
        "Time Diff": 1.802
    },
    {
        "Node IP": "162.55.2.xxx",
        "Block ID": 3731738,
        "Time Diff": 1.808
    },
    {
        "Node IP": "45.15.157.xxx",
        "Block ID": 3731738,
        "Time Diff": 1.907
    },
    {
        "Node IP": "178.62.224.xxx",
        "Block ID": 3731738,
        "Time Diff": 1.908
    },
    {
        "Node IP": "188.117.156.xxx",
        "Block ID": 3731738,
        "Time Diff": 1.928
    },
    {
        "Node IP": "144.91.66.xxx",
        "Block ID": 3731738,
        "Time Diff": 1.964
    },
    {
        "Node IP": "77.89.123.xxx",
        "Block ID": 3731738,
        "Time Diff": 1.972
    },
    {
        "Node IP": "207.180.254.xxx",
        "Block ID": 3731738,
        "Time Diff": 2.047
    },
    {
        "Node IP": "202.61.199.xxx",
        "Block ID": 3731738,
        "Time Diff": 2.18
    },
    {
        "Node IP": "51.79.19.xxx",
        "Block ID": 3731738,
        "Time Diff": 2.265
    },
    {
        "Node IP": "95.217.61.xxx",
        "Block ID": 3731738,
        "Time Diff": 2.276
    },
    {
        "Node IP": "167.86.73.xxx",
        "Block ID": 3731738,
        "Time Diff": 2.35
    },
    {
        "Node IP": "123.19.4.xxx",
        "Block ID": 3731738,
        "Time Diff": 2.401
    },
    {
        "Node IP": "173.249.26.xxx",
        "Block ID": 3731738,
        "Time Diff": 2.427
    },
    {
        "Node IP": "38.242.209.xxx",
        "Block ID": 3731738,
        "Time Diff": 2.503
    },
    {
        "Node IP": "78.46.80.xxx",
        "Block ID": 3731738,
        "Time Diff": 2.58
    },
    {
        "Last Updated": "2024-06-21T05:33:46.083332"
    }
]