[
    {
        "Node IP": "84.59.129.xxx",
        "Block ID": 2276094,
        "Time Diff": 4.847
    },
    {
        "Node IP": "185.7.170.xxx",
        "Block ID": 2276094,
        "Time Diff": 5.258
    },
    {
        "Node IP": "189.217.80.xxx",
        "Block ID": 2276094,
        "Time Diff": 5.741
    },
    {
        "Node IP": "37.27.68.xxx",
        "Block ID": 2276094,
        "Time Diff": 5.924
    },
    {
        "Node IP": "79.190.201.xxx",
        "Block ID": 2276094,
        "Time Diff": 6.072
    },
    {
        "Node IP": "73.156.3.xxx",
        "Block ID": 2276094,
        "Time Diff": 6.155
    },
    {
        "Node IP": "89.77.74.xxx",
        "Block ID": 2276094,
        "Time Diff": 6.609
    },
    {
        "Node IP": "162.19.99.xxx",
        "Block ID": 2276094,
        "Time Diff": 6.742
    },
    {
        "Node IP": "78.46.80.xxx",
        "Block ID": 2276094,
        "Time Diff": 6.892
    },
    {
        "Node IP": "96.250.163.xxx",
        "Block ID": 2276094,
        "Time Diff": 7.099
    },
    {
        "Node IP": "161.97.146.xxx",
        "Block ID": 2276094,
        "Time Diff": 7.207
    },
    {
        "Node IP": "65.25.183.xxx",
        "Block ID": 2276094,
        "Time Diff": 7.315
    },
    {
        "Node IP": "74.50.77.xxx",
        "Block ID": 2276094,
        "Time Diff": 7.352
    },
    {
        "Node IP": "58.169.131.xxx",
        "Block ID": 2276094,
        "Time Diff": 7.377
    },
    {
        "Node IP": "98.122.100.xxx",
        "Block ID": 2276094,
        "Time Diff": 7.832
    },
    {
        "Node IP": "188.214.130.xxx",
        "Block ID": 2276094,
        "Time Diff": 7.836
    },
    {
        "Node IP": "185.166.169.xxx",
        "Block ID": 2276094,
        "Time Diff": 7.836
    },
    {
        "Node IP": "188.117.173.xxx",
        "Block ID": 2276094,
        "Time Diff": 7.868
    },
    {
        "Node IP": "83.5.181.xxx",
        "Block ID": 2276094,
        "Time Diff": 7.974
    },
    {
        "Node IP": "61.231.228.xxx",
        "Block ID": 2276094,
        "Time Diff": 7.997
    },
    {
        "Node IP": "74.50.76.xxx",
        "Block ID": 2276094,
        "Time Diff": 8.084
    },
    {
        "Node IP": "64.20.33.xxx",
        "Block ID": 2276094,
        "Time Diff": 8.269
    },
    {
        "Node IP": "93.180.190.xxx",
        "Block ID": 2276094,
        "Time Diff": 8.321
    },
    {
        "Node IP": "144.76.3.xxx",
        "Block ID": 2276094,
        "Time Diff": 8.524
    },
    {
        "Node IP": "103.106.58.xxx",
        "Block ID": 2276094,
        "Time Diff": 8.571
    },
    {
        "Node IP": "74.50.94.xxx",
        "Block ID": 2276094,
        "Time Diff": 8.615
    },
    {
        "Node IP": "176.109.50.xxx",
        "Block ID": 2276094,
        "Time Diff": 8.916
    },
    {
        "Node IP": "177.54.146.xxx",
        "Block ID": 2276094,
        "Time Diff": 9.022
    },
    {
        "Node IP": "109.205.213.xxx",
        "Block ID": 2276094,
        "Time Diff": 9.182
    },
    {
        "Node IP": "88.99.94.xxx",
        "Block ID": 2276094,
        "Time Diff": 9.285
    },
    {
        "Node IP": "67.217.49.xxx",
        "Block ID": 2276094,
        "Time Diff": 9.4
    },
    {
        "Node IP": "135.181.246.xxx",
        "Block ID": 2276094,
        "Time Diff": 9.446
    },
    {
        "Node IP": "66.45.225.xxx",
        "Block ID": 2276094,
        "Time Diff": 9.471
    },
    {
        "Node IP": "161.97.141.xxx",
        "Block ID": 2276094,
        "Time Diff": 9.474
    },
    {
        "Node IP": "159.196.169.xxx",
        "Block ID": 2276094,
        "Time Diff": 9.524
    },
    {
        "Node IP": "144.168.61.xxx",
        "Block ID": 2276094,
        "Time Diff": 9.748
    },
    {
        "Node IP": "160.202.130.xxx",
        "Block ID": 2276094,
        "Time Diff": 9.806
    },
    {
        "Node IP": "213.76.115.xxx",
        "Block ID": 2276094,
        "Time Diff": 9.973
    },
    {
        "Node IP": "144.208.193.xxx",
        "Block ID": 2276094,
        "Time Diff": 10.068
    },
    {
        "Node IP": "27.109.214.xxx",
        "Block ID": 2276094,
        "Time Diff": 10.079
    },
    {
        "Node IP": "213.239.234.xxx",
        "Block ID": 2276094,
        "Time Diff": 10.144
    },
    {
        "Node IP": "43.133.227.xxx",
        "Block ID": 2276094,
        "Time Diff": 10.177
    },
    {
        "Node IP": "84.247.185.xxx",
        "Block ID": 2276094,
        "Time Diff": 10.32
    },
    {
        "Node IP": "129.226.81.xxx",
        "Block ID": 2276094,
        "Time Diff": 10.479
    },
    {
        "Node IP": "138.201.36.xxx",
        "Block ID": 2276094,
        "Time Diff": 10.588
    },
    {
        "Node IP": "113.247.108.xxx",
        "Block ID": 2276094,
        "Time Diff": 10.599
    },
    {
        "Node IP": "207.244.242.xxx",
        "Block ID": 2276094,
        "Time Diff": 10.631
    },
    {
        "Node IP": "43.134.28.xxx",
        "Block ID": 2276094,
        "Time Diff": 10.733
    },
    {
        "Node IP": "43.133.70.xxx",
        "Block ID": 2276094,
        "Time Diff": 10.826
    },
    {
        "Node IP": "43.128.146.xxx",
        "Block ID": 2276094,
        "Time Diff": 10.859
    },
    {
        "Xenobi Ranking": 13
    },
    {
        "Last Updated": "2024-03-24T21:36:24.385756"
    }
]