[
    {
        "Node IP": "97.85.41.xxx",
        "Block ID": 2326923,
        "Time Diff": 2.942
    },
    {
        "Node IP": "162.19.99.xxx",
        "Block ID": 2326923,
        "Time Diff": 3.776
    },
    {
        "Node IP": "65.21.69.xxx",
        "Block ID": 2326923,
        "Time Diff": 3.993
    },
    {
        "Node IP": "64.20.33.xxx",
        "Block ID": 2326923,
        "Time Diff": 4.195
    },
    {
        "Node IP": "65.25.183.xxx",
        "Block ID": 2326923,
        "Time Diff": 4.264
    },
    {
        "Node IP": "74.50.76.xxx",
        "Block ID": 2326923,
        "Time Diff": 4.325
    },
    {
        "Node IP": "98.122.100.xxx",
        "Block ID": 2326923,
        "Time Diff": 4.39
    },
    {
        "Node IP": "188.214.130.xxx",
        "Block ID": 2326923,
        "Time Diff": 4.714
    },
    {
        "Node IP": "190.242.27.xxx",
        "Block ID": 2326923,
        "Time Diff": 5.479
    },
    {
        "Node IP": "77.253.146.xxx",
        "Block ID": 2326923,
        "Time Diff": 5.829
    },
    {
        "Node IP": "144.126.133.xxx",
        "Block ID": 2326923,
        "Time Diff": 5.852
    },
    {
        "Node IP": "64.20.46.xxx",
        "Block ID": 2326923,
        "Time Diff": 6.045
    },
    {
        "Node IP": "65.109.67.xxx",
        "Block ID": 2326923,
        "Time Diff": 6.13
    },
    {
        "Node IP": "207.244.242.xxx",
        "Block ID": 2326923,
        "Time Diff": 6.162
    },
    {
        "Node IP": "96.250.163.xxx",
        "Block ID": 2326923,
        "Time Diff": 6.174
    },
    {
        "Node IP": "85.215.99.xxx",
        "Block ID": 2326923,
        "Time Diff": 7.16
    },
    {
        "Node IP": "34.134.196.xxx",
        "Block ID": 2326923,
        "Time Diff": 7.703
    },
    {
        "Node IP": "195.201.112.xxx",
        "Block ID": 2326923,
        "Time Diff": 7.722
    },
    {
        "Node IP": "95.217.32.xxx",
        "Block ID": 2326923,
        "Time Diff": 9.103
    },
    {
        "Node IP": "45.250.253.xxx",
        "Block ID": 2326923,
        "Time Diff": 9.46
    },
    {
        "Node IP": "129.153.23.xxx",
        "Block ID": 2326923,
        "Time Diff": 11.92
    },
    {
        "Node IP": "65.109.98.xxx",
        "Block ID": 2326923,
        "Time Diff": 12.451
    },
    {
        "Node IP": "213.199.53.xxx",
        "Block ID": 2326923,
        "Time Diff": 15.207
    },
    {
        "Node IP": "213.199.46.xxx",
        "Block ID": 2326923,
        "Time Diff": 18.383
    },
    {
        "Node IP": "37.27.68.xxx",
        "Block ID": 2326922,
        "Time Diff": 4.935
    },
    {
        "Node IP": "185.7.170.xxx",
        "Block ID": 2326922,
        "Time Diff": 5.356
    },
    {
        "Node IP": "189.217.80.xxx",
        "Block ID": 2326922,
        "Time Diff": 5.614
    },
    {
        "Node IP": "58.169.131.xxx",
        "Block ID": 2326922,
        "Time Diff": 5.988
    },
    {
        "Node IP": "207.188.7.xxx",
        "Block ID": 2326922,
        "Time Diff": 6.03
    },
    {
        "Node IP": "73.156.3.xxx",
        "Block ID": 2326922,
        "Time Diff": 6.091
    },
    {
        "Node IP": "84.59.129.xxx",
        "Block ID": 2326922,
        "Time Diff": 6.098
    },
    {
        "Node IP": "178.217.199.xxx",
        "Block ID": 2326922,
        "Time Diff": 6.233
    },
    {
        "Node IP": "116.30.10.xxx",
        "Block ID": 2326922,
        "Time Diff": 6.306
    },
    {
        "Node IP": "103.106.58.xxx",
        "Block ID": 2326922,
        "Time Diff": 6.49
    },
    {
        "Node IP": "27.109.214.xxx",
        "Block ID": 2326922,
        "Time Diff": 6.529
    },
    {
        "Node IP": "74.50.77.xxx",
        "Block ID": 2326922,
        "Time Diff": 6.844
    },
    {
        "Node IP": "213.239.234.xxx",
        "Block ID": 2326922,
        "Time Diff": 7.158
    },
    {
        "Node IP": "176.109.50.xxx",
        "Block ID": 2326922,
        "Time Diff": 7.179
    },
    {
        "Node IP": "61.231.228.xxx",
        "Block ID": 2326922,
        "Time Diff": 7.187
    },
    {
        "Node IP": "93.180.190.xxx",
        "Block ID": 2326922,
        "Time Diff": 7.411
    },
    {
        "Node IP": "98.226.9.xxx",
        "Block ID": 2326922,
        "Time Diff": 7.572
    },
    {
        "Node IP": "89.77.74.xxx",
        "Block ID": 2326922,
        "Time Diff": 7.645
    },
    {
        "Node IP": "37.27.51.xxx",
        "Block ID": 2326922,
        "Time Diff": 7.672
    },
    {
        "Node IP": "144.76.3.xxx",
        "Block ID": 2326922,
        "Time Diff": 7.693
    },
    {
        "Node IP": "74.50.94.xxx",
        "Block ID": 2326922,
        "Time Diff": 7.747
    },
    {
        "Node IP": "159.196.169.xxx",
        "Block ID": 2326922,
        "Time Diff": 7.808
    },
    {
        "Node IP": "161.97.146.xxx",
        "Block ID": 2326922,
        "Time Diff": 7.857
    },
    {
        "Node IP": "83.5.181.xxx",
        "Block ID": 2326922,
        "Time Diff": 7.897
    },
    {
        "Node IP": "135.181.246.xxx",
        "Block ID": 2326922,
        "Time Diff": 7.899
    },
    {
        "Node IP": "185.166.169.xxx",
        "Block ID": 2326922,
        "Time Diff": 8.101
    },
    {
        "Xenobi Ranking": 36
    },
    {
        "Last Updated": "2024-03-27T19:36:07.103592"
    }
]