[
    {
        "Node IP": "69.10.52.xxx",
        "Block ID": 2968999,
        "Time Diff": 11.324
    },
    {
        "Node IP": "185.7.170.xxx",
        "Block ID": 2968999,
        "Time Diff": 11.331
    },
    {
        "Node IP": "113.162.133.xxx",
        "Block ID": 2968999,
        "Time Diff": 11.958
    },
    {
        "Node IP": "173.208.193.xxx",
        "Block ID": 2968999,
        "Time Diff": 12.072
    },
    {
        "Node IP": "64.121.75.xxx",
        "Block ID": 2968999,
        "Time Diff": 12.307
    },
    {
        "Node IP": "83.5.234.xxx",
        "Block ID": 2968999,
        "Time Diff": 12.348
    },
    {
        "Node IP": "73.156.3.xxx",
        "Block ID": 2968999,
        "Time Diff": 12.411
    },
    {
        "Node IP": "37.27.68.xxx",
        "Block ID": 2968999,
        "Time Diff": 13.051
    },
    {
        "Node IP": "189.217.80.xxx",
        "Block ID": 2968999,
        "Time Diff": 13.104
    },
    {
        "Node IP": "97.85.41.xxx",
        "Block ID": 2968999,
        "Time Diff": 13.25
    },
    {
        "Node IP": "109.205.213.xxx",
        "Block ID": 2968999,
        "Time Diff": 13.294
    },
    {
        "Node IP": "58.169.131.xxx",
        "Block ID": 2968999,
        "Time Diff": 13.348
    },
    {
        "Node IP": "67.85.107.xxx",
        "Block ID": 2968999,
        "Time Diff": 13.53
    },
    {
        "Node IP": "57.128.95.xxx",
        "Block ID": 2968999,
        "Time Diff": 13.826
    },
    {
        "Node IP": "79.190.201.xxx",
        "Block ID": 2968999,
        "Time Diff": 14.048
    },
    {
        "Node IP": "116.30.11.xxx",
        "Block ID": 2968999,
        "Time Diff": 14.235
    },
    {
        "Node IP": "65.21.69.xxx",
        "Block ID": 2968999,
        "Time Diff": 14.274
    },
    {
        "Node IP": "176.109.50.xxx",
        "Block ID": 2968999,
        "Time Diff": 14.812
    },
    {
        "Node IP": "162.19.99.xxx",
        "Block ID": 2968999,
        "Time Diff": 14.854
    },
    {
        "Node IP": "74.50.77.xxx",
        "Block ID": 2968999,
        "Time Diff": 15.094
    },
    {
        "Node IP": "161.97.146.xxx",
        "Block ID": 2968999,
        "Time Diff": 15.423
    },
    {
        "Node IP": "27.109.214.xxx",
        "Block ID": 2968999,
        "Time Diff": 16.204
    },
    {
        "Node IP": "74.50.76.xxx",
        "Block ID": 2968999,
        "Time Diff": 16.265
    },
    {
        "Node IP": "205.209.114.xxx",
        "Block ID": 2968999,
        "Time Diff": 16.55
    },
    {
        "Node IP": "135.181.246.xxx",
        "Block ID": 2968999,
        "Time Diff": 16.576
    },
    {
        "Node IP": "95.217.61.xxx",
        "Block ID": 2968999,
        "Time Diff": 16.742
    },
    {
        "Node IP": "49.12.172.xxx",
        "Block ID": 2968999,
        "Time Diff": 16.939
    },
    {
        "Node IP": "162.246.18.xxx",
        "Block ID": 2968999,
        "Time Diff": 17.156
    },
    {
        "Node IP": "61.231.226.xxx",
        "Block ID": 2968999,
        "Time Diff": 17.326
    },
    {
        "Node IP": "185.22.10.xxx",
        "Block ID": 2968999,
        "Time Diff": 17.576
    },
    {
        "Node IP": "162.250.127.xxx",
        "Block ID": 2968999,
        "Time Diff": 17.87
    },
    {
        "Node IP": "69.10.51.xxx",
        "Block ID": 2968999,
        "Time Diff": 18.095
    },
    {
        "Node IP": "206.72.207.xxx",
        "Block ID": 2968999,
        "Time Diff": 18.195
    },
    {
        "Node IP": "64.20.33.xxx",
        "Block ID": 2968999,
        "Time Diff": 18.28
    },
    {
        "Node IP": "67.217.49.xxx",
        "Block ID": 2968999,
        "Time Diff": 18.402
    },
    {
        "Node IP": "188.214.130.xxx",
        "Block ID": 2968999,
        "Time Diff": 18.899
    },
    {
        "Node IP": "213.239.194.xxx",
        "Block ID": 2968999,
        "Time Diff": 19.337
    },
    {
        "Node IP": "66.45.234.xxx",
        "Block ID": 2968999,
        "Time Diff": 19.349
    },
    {
        "Node IP": "67.217.54.xxx",
        "Block ID": 2968999,
        "Time Diff": 19.491
    },
    {
        "Node IP": "45.15.157.xxx",
        "Block ID": 2968999,
        "Time Diff": 19.524
    },
    {
        "Node IP": "177.54.146.xxx",
        "Block ID": 2968999,
        "Time Diff": 19.563
    },
    {
        "Node IP": "198.84.243.xxx",
        "Block ID": 2968999,
        "Time Diff": 19.66
    },
    {
        "Node IP": "162.250.125.xxx",
        "Block ID": 2968999,
        "Time Diff": 19.806
    },
    {
        "Node IP": "205.209.117.xxx",
        "Block ID": 2968999,
        "Time Diff": 20.318
    },
    {
        "Node IP": "64.20.62.xxx",
        "Block ID": 2968999,
        "Time Diff": 20.408
    },
    {
        "Node IP": "34.174.159.xxx",
        "Block ID": 2968999,
        "Time Diff": 20.411
    },
    {
        "Node IP": "161.97.141.xxx",
        "Block ID": 2968999,
        "Time Diff": 20.603
    },
    {
        "Node IP": "74.50.94.xxx",
        "Block ID": 2968999,
        "Time Diff": 20.658
    },
    {
        "Node IP": "37.27.51.xxx",
        "Block ID": 2968999,
        "Time Diff": 20.743
    },
    {
        "Node IP": "144.217.11.xxx",
        "Block ID": 2968999,
        "Time Diff": 21.263
    },
    {
        "Xenobi Ranking": 20
    },
    {
        "Last Updated": "2024-04-19T20:23:19.973784"
    }
]