[
    {
        "Node IP": "37.27.68.xxx",
        "Block ID": 2041870,
        "Time Diff": 3.162
    },
    {
        "Node IP": "97.85.41.xxx",
        "Block ID": 2041870,
        "Time Diff": 3.305
    },
    {
        "Node IP": "58.169.131.xxx",
        "Block ID": 2041870,
        "Time Diff": 3.676
    },
    {
        "Node IP": "162.19.99.xxx",
        "Block ID": 2041870,
        "Time Diff": 3.684
    },
    {
        "Node IP": "189.217.92.xxx",
        "Block ID": 2041870,
        "Time Diff": 3.883
    },
    {
        "Node IP": "213.239.234.xxx",
        "Block ID": 2041870,
        "Time Diff": 3.937
    },
    {
        "Node IP": "79.190.201.xxx",
        "Block ID": 2041870,
        "Time Diff": 3.977
    },
    {
        "Node IP": "96.250.163.xxx",
        "Block ID": 2041870,
        "Time Diff": 3.999
    },
    {
        "Node IP": "185.7.170.xxx",
        "Block ID": 2041870,
        "Time Diff": 4.154
    },
    {
        "Node IP": "178.217.199.xxx",
        "Block ID": 2041870,
        "Time Diff": 4.191
    },
    {
        "Node IP": "84.59.129.xxx",
        "Block ID": 2041870,
        "Time Diff": 4.428
    },
    {
        "Node IP": "69.10.34.xxx",
        "Block ID": 2041870,
        "Time Diff": 4.467
    },
    {
        "Node IP": "161.97.146.xxx",
        "Block ID": 2041870,
        "Time Diff": 4.564
    },
    {
        "Node IP": "5.182.87.xxx",
        "Block ID": 2041870,
        "Time Diff": 4.573
    },
    {
        "Node IP": "188.214.130.xxx",
        "Block ID": 2041870,
        "Time Diff": 4.643
    },
    {
        "Node IP": "31.179.130.xxx",
        "Block ID": 2041870,
        "Time Diff": 4.684
    },
    {
        "Node IP": "74.50.76.xxx",
        "Block ID": 2041870,
        "Time Diff": 4.802
    },
    {
        "Node IP": "144.76.3.xxx",
        "Block ID": 2041870,
        "Time Diff": 4.835
    },
    {
        "Node IP": "185.166.170.xxx",
        "Block ID": 2041870,
        "Time Diff": 4.947
    },
    {
        "Node IP": "98.122.100.xxx",
        "Block ID": 2041870,
        "Time Diff": 4.977
    },
    {
        "Node IP": "83.6.123.xxx",
        "Block ID": 2041870,
        "Time Diff": 4.995
    },
    {
        "Node IP": "116.202.173.xxx",
        "Block ID": 2041870,
        "Time Diff": 5.045
    },
    {
        "Node IP": "213.76.115.xxx",
        "Block ID": 2041870,
        "Time Diff": 5.068
    },
    {
        "Node IP": "65.25.183.xxx",
        "Block ID": 2041870,
        "Time Diff": 5.386
    },
    {
        "Node IP": "74.50.77.xxx",
        "Block ID": 2041870,
        "Time Diff": 5.534
    },
    {
        "Node IP": "160.202.130.xxx",
        "Block ID": 2041870,
        "Time Diff": 5.633
    },
    {
        "Node IP": "64.20.33.xxx",
        "Block ID": 2041870,
        "Time Diff": 5.685
    },
    {
        "Node IP": "93.180.190.xxx",
        "Block ID": 2041870,
        "Time Diff": 5.784
    },
    {
        "Node IP": "43.134.28.xxx",
        "Block ID": 2041870,
        "Time Diff": 5.888
    },
    {
        "Node IP": "144.168.61.xxx",
        "Block ID": 2041870,
        "Time Diff": 5.917
    },
    {
        "Node IP": "154.38.162.xxx",
        "Block ID": 2041870,
        "Time Diff": 5.917
    },
    {
        "Node IP": "43.134.21.xxx",
        "Block ID": 2041870,
        "Time Diff": 5.933
    },
    {
        "Node IP": "64.20.46.xxx",
        "Block ID": 2041870,
        "Time Diff": 5.945
    },
    {
        "Node IP": "188.137.48.xxx",
        "Block ID": 2041870,
        "Time Diff": 6.008
    },
    {
        "Node IP": "14.248.82.xxx",
        "Block ID": 2041870,
        "Time Diff": 6.044
    },
    {
        "Node IP": "129.226.81.xxx",
        "Block ID": 2041870,
        "Time Diff": 6.067
    },
    {
        "Node IP": "43.133.227.xxx",
        "Block ID": 2041870,
        "Time Diff": 6.137
    },
    {
        "Node IP": "37.27.61.xxx",
        "Block ID": 2041870,
        "Time Diff": 6.147
    },
    {
        "Node IP": "84.247.185.xxx",
        "Block ID": 2041870,
        "Time Diff": 6.169
    },
    {
        "Node IP": "190.242.27.xxx",
        "Block ID": 2041870,
        "Time Diff": 6.274
    },
    {
        "Node IP": "84.247.168.xxx",
        "Block ID": 2041870,
        "Time Diff": 6.355
    },
    {
        "Node IP": "207.244.242.xxx",
        "Block ID": 2041870,
        "Time Diff": 6.423
    },
    {
        "Node IP": "119.28.188.xxx",
        "Block ID": 2041870,
        "Time Diff": 6.521
    },
    {
        "Node IP": "43.128.146.xxx",
        "Block ID": 2041870,
        "Time Diff": 6.564
    },
    {
        "Node IP": "92.205.177.xxx",
        "Block ID": 2041870,
        "Time Diff": 6.643
    },
    {
        "Node IP": "43.163.8.xxx",
        "Block ID": 2041870,
        "Time Diff": 6.676
    },
    {
        "Node IP": "43.133.70.xxx",
        "Block ID": 2041870,
        "Time Diff": 6.693
    },
    {
        "Node IP": "43.134.90.xxx",
        "Block ID": 2041870,
        "Time Diff": 6.717
    },
    {
        "Node IP": "65.109.67.xxx",
        "Block ID": 2041870,
        "Time Diff": 6.761
    },
    {
        "Node IP": "85.215.99.xxx",
        "Block ID": 2041870,
        "Time Diff": 6.861
    },
    {
        "Xenobi Ranking": 25
    },
    {
        "Last Updated": "2024-03-15T14:29:38.274169"
    }
]