[
    {
        "Node IP": "97.85.41.xxx",
        "Block ID": 2106742,
        "Time Diff": 3.659
    },
    {
        "Node IP": "37.27.68.xxx",
        "Block ID": 2106742,
        "Time Diff": 4.052
    },
    {
        "Node IP": "27.109.214.xxx",
        "Block ID": 2106742,
        "Time Diff": 4.389
    },
    {
        "Node IP": "189.217.92.xxx",
        "Block ID": 2106742,
        "Time Diff": 4.441
    },
    {
        "Node IP": "79.190.201.xxx",
        "Block ID": 2106742,
        "Time Diff": 4.471
    },
    {
        "Node IP": "58.169.131.xxx",
        "Block ID": 2106742,
        "Time Diff": 4.501
    },
    {
        "Node IP": "162.19.99.xxx",
        "Block ID": 2106742,
        "Time Diff": 4.669
    },
    {
        "Node IP": "185.7.170.xxx",
        "Block ID": 2106742,
        "Time Diff": 4.744
    },
    {
        "Node IP": "96.250.163.xxx",
        "Block ID": 2106742,
        "Time Diff": 4.781
    },
    {
        "Node IP": "88.99.94.xxx",
        "Block ID": 2106742,
        "Time Diff": 4.946
    },
    {
        "Node IP": "178.217.199.xxx",
        "Block ID": 2106742,
        "Time Diff": 5.573
    },
    {
        "Node IP": "83.6.123.xxx",
        "Block ID": 2106742,
        "Time Diff": 5.618
    },
    {
        "Node IP": "135.181.246.xxx",
        "Block ID": 2106742,
        "Time Diff": 5.741
    },
    {
        "Node IP": "161.97.146.xxx",
        "Block ID": 2106742,
        "Time Diff": 5.791
    },
    {
        "Node IP": "74.50.76.xxx",
        "Block ID": 2106742,
        "Time Diff": 5.832
    },
    {
        "Node IP": "188.214.130.xxx",
        "Block ID": 2106742,
        "Time Diff": 5.91
    },
    {
        "Node IP": "113.176.163.xxx",
        "Block ID": 2106742,
        "Time Diff": 5.913
    },
    {
        "Node IP": "98.226.9.xxx",
        "Block ID": 2106742,
        "Time Diff": 6.135
    },
    {
        "Node IP": "37.27.61.xxx",
        "Block ID": 2106742,
        "Time Diff": 6.211
    },
    {
        "Node IP": "144.76.3.xxx",
        "Block ID": 2106742,
        "Time Diff": 6.258
    },
    {
        "Node IP": "84.59.129.xxx",
        "Block ID": 2106742,
        "Time Diff": 6.347
    },
    {
        "Node IP": "103.156.58.xxx",
        "Block ID": 2106742,
        "Time Diff": 6.503
    },
    {
        "Node IP": "162.55.2.xxx",
        "Block ID": 2106742,
        "Time Diff": 6.697
    },
    {
        "Node IP": "14.248.82.xxx",
        "Block ID": 2106742,
        "Time Diff": 6.711
    },
    {
        "Node IP": "78.46.80.xxx",
        "Block ID": 2106742,
        "Time Diff": 6.772
    },
    {
        "Node IP": "74.50.77.xxx",
        "Block ID": 2106742,
        "Time Diff": 6.823
    },
    {
        "Node IP": "43.134.28.xxx",
        "Block ID": 2106742,
        "Time Diff": 6.854
    },
    {
        "Node IP": "109.205.213.xxx",
        "Block ID": 2106742,
        "Time Diff": 6.893
    },
    {
        "Node IP": "144.208.193.xxx",
        "Block ID": 2106742,
        "Time Diff": 6.991
    },
    {
        "Node IP": "116.202.173.xxx",
        "Block ID": 2106742,
        "Time Diff": 7.057
    },
    {
        "Node IP": "103.106.58.xxx",
        "Block ID": 2106742,
        "Time Diff": 7.059
    },
    {
        "Node IP": "98.122.100.xxx",
        "Block ID": 2106742,
        "Time Diff": 7.063
    },
    {
        "Node IP": "144.168.61.xxx",
        "Block ID": 2106742,
        "Time Diff": 7.085
    },
    {
        "Node IP": "119.28.188.xxx",
        "Block ID": 2106742,
        "Time Diff": 7.154
    },
    {
        "Node IP": "64.20.46.xxx",
        "Block ID": 2106742,
        "Time Diff": 7.25
    },
    {
        "Node IP": "160.202.130.xxx",
        "Block ID": 2106742,
        "Time Diff": 7.254
    },
    {
        "Node IP": "64.20.33.xxx",
        "Block ID": 2106742,
        "Time Diff": 7.512
    },
    {
        "Node IP": "129.226.81.xxx",
        "Block ID": 2106742,
        "Time Diff": 7.524
    },
    {
        "Node IP": "5.182.87.xxx",
        "Block ID": 2106742,
        "Time Diff": 7.534
    },
    {
        "Node IP": "154.38.162.xxx",
        "Block ID": 2106742,
        "Time Diff": 7.535
    },
    {
        "Node IP": "65.109.112.xxx",
        "Block ID": 2106742,
        "Time Diff": 7.587
    },
    {
        "Node IP": "65.109.67.xxx",
        "Block ID": 2106742,
        "Time Diff": 7.653
    },
    {
        "Node IP": "43.128.146.xxx",
        "Block ID": 2106742,
        "Time Diff": 7.685
    },
    {
        "Node IP": "69.10.38.xxx",
        "Block ID": 2106742,
        "Time Diff": 7.695
    },
    {
        "Node IP": "43.163.8.xxx",
        "Block ID": 2106742,
        "Time Diff": 7.718
    },
    {
        "Node IP": "84.247.168.xxx",
        "Block ID": 2106742,
        "Time Diff": 7.721
    },
    {
        "Node IP": "65.108.134.xxx",
        "Block ID": 2106742,
        "Time Diff": 7.736
    },
    {
        "Node IP": "213.76.115.xxx",
        "Block ID": 2106742,
        "Time Diff": 7.798
    },
    {
        "Node IP": "207.244.242.xxx",
        "Block ID": 2106742,
        "Time Diff": 7.805
    },
    {
        "Node IP": "144.126.133.xxx",
        "Block ID": 2106742,
        "Time Diff": 8.013
    },
    {
        "Xenobi Ranking": 26
    },
    {
        "Last Updated": "2024-03-17T14:07:24.777765"
    }
]