[
    {
        "Node IP": "181.214.147.xxx",
        "Block ID": 3296800,
        "Time Diff": 2.88
    },
    {
        "Node IP": "37.27.68.xxx",
        "Block ID": 3296800,
        "Time Diff": 3.022
    },
    {
        "Node IP": "66.23.234.xxx",
        "Block ID": 3296800,
        "Time Diff": 3.041
    },
    {
        "Node IP": "185.7.170.xxx",
        "Block ID": 3296800,
        "Time Diff": 3.178
    },
    {
        "Node IP": "64.121.75.xxx",
        "Block ID": 3296800,
        "Time Diff": 3.342
    },
    {
        "Node IP": "37.27.61.xxx",
        "Block ID": 3296800,
        "Time Diff": 3.365
    },
    {
        "Node IP": "144.208.193.xxx",
        "Block ID": 3296800,
        "Time Diff": 3.393
    },
    {
        "Node IP": "73.156.3.xxx",
        "Block ID": 3296800,
        "Time Diff": 3.416
    },
    {
        "Node IP": "65.21.69.xxx",
        "Block ID": 3296800,
        "Time Diff": 3.474
    },
    {
        "Node IP": "173.208.193.xxx",
        "Block ID": 3296800,
        "Time Diff": 3.503
    },
    {
        "Node IP": "58.169.131.xxx",
        "Block ID": 3296800,
        "Time Diff": 3.511
    },
    {
        "Node IP": "188.137.48.xxx",
        "Block ID": 3296800,
        "Time Diff": 3.514
    },
    {
        "Node IP": "188.117.173.xxx",
        "Block ID": 3296800,
        "Time Diff": 3.54
    },
    {
        "Node IP": "57.128.95.xxx",
        "Block ID": 3296800,
        "Time Diff": 3.565
    },
    {
        "Node IP": "162.19.99.xxx",
        "Block ID": 3296800,
        "Time Diff": 3.595
    },
    {
        "Node IP": "189.217.80.xxx",
        "Block ID": 3296800,
        "Time Diff": 3.78
    },
    {
        "Node IP": "188.117.156.xxx",
        "Block ID": 3296800,
        "Time Diff": 3.789
    },
    {
        "Node IP": "79.190.201.xxx",
        "Block ID": 3296800,
        "Time Diff": 3.799
    },
    {
        "Node IP": "14.245.215.xxx",
        "Block ID": 3296800,
        "Time Diff": 3.82
    },
    {
        "Node IP": "97.85.41.xxx",
        "Block ID": 3296800,
        "Time Diff": 3.842
    },
    {
        "Node IP": "74.50.77.xxx",
        "Block ID": 3296800,
        "Time Diff": 3.912
    },
    {
        "Node IP": "109.205.213.xxx",
        "Block ID": 3296800,
        "Time Diff": 3.958
    },
    {
        "Node IP": "65.108.134.xxx",
        "Block ID": 3296800,
        "Time Diff": 4.092
    },
    {
        "Node IP": "65.109.112.xxx",
        "Block ID": 3296800,
        "Time Diff": 4.113
    },
    {
        "Node IP": "65.109.114.xxx",
        "Block ID": 3296800,
        "Time Diff": 4.213
    },
    {
        "Node IP": "205.209.126.xxx",
        "Block ID": 3296800,
        "Time Diff": 4.261
    },
    {
        "Node IP": "67.85.107.xxx",
        "Block ID": 3296800,
        "Time Diff": 4.286
    },
    {
        "Node IP": "176.109.50.xxx",
        "Block ID": 3296800,
        "Time Diff": 4.3
    },
    {
        "Node IP": "206.72.207.xxx",
        "Block ID": 3296800,
        "Time Diff": 4.327
    },
    {
        "Node IP": "177.54.146.xxx",
        "Block ID": 3296800,
        "Time Diff": 4.371
    },
    {
        "Node IP": "66.23.236.xxx",
        "Block ID": 3296800,
        "Time Diff": 4.393
    },
    {
        "Node IP": "27.109.214.xxx",
        "Block ID": 3296800,
        "Time Diff": 4.542
    },
    {
        "Node IP": "49.12.172.xxx",
        "Block ID": 3296800,
        "Time Diff": 4.542
    },
    {
        "Node IP": "212.102.58.xxx",
        "Block ID": 3296800,
        "Time Diff": 4.555
    },
    {
        "Node IP": "64.20.45.xxx",
        "Block ID": 3296800,
        "Time Diff": 4.593
    },
    {
        "Node IP": "205.209.110.xxx",
        "Block ID": 3296800,
        "Time Diff": 4.594
    },
    {
        "Node IP": "216.158.226.xxx",
        "Block ID": 3296800,
        "Time Diff": 4.606
    },
    {
        "Node IP": "67.217.48.xxx",
        "Block ID": 3296800,
        "Time Diff": 4.657
    },
    {
        "Node IP": "161.97.146.xxx",
        "Block ID": 3296800,
        "Time Diff": 4.69
    },
    {
        "Node IP": "74.50.76.xxx",
        "Block ID": 3296800,
        "Time Diff": 4.707
    },
    {
        "Node IP": "74.50.94.xxx",
        "Block ID": 3296800,
        "Time Diff": 4.754
    },
    {
        "Node IP": "213.76.115.xxx",
        "Block ID": 3296800,
        "Time Diff": 4.767
    },
    {
        "Node IP": "162.250.125.xxx",
        "Block ID": 3296800,
        "Time Diff": 4.788
    },
    {
        "Node IP": "135.181.246.xxx",
        "Block ID": 3296800,
        "Time Diff": 4.79
    },
    {
        "Node IP": "69.10.51.xxx",
        "Block ID": 3296800,
        "Time Diff": 4.805
    },
    {
        "Node IP": "185.22.10.xxx",
        "Block ID": 3296800,
        "Time Diff": 4.863
    },
    {
        "Node IP": "185.166.169.xxx",
        "Block ID": 3296800,
        "Time Diff": 4.92
    },
    {
        "Node IP": "67.217.54.xxx",
        "Block ID": 3296800,
        "Time Diff": 4.923
    },
    {
        "Node IP": "66.45.234.xxx",
        "Block ID": 3296800,
        "Time Diff": 4.992
    },
    {
        "Node IP": "66.45.225.xxx",
        "Block ID": 3296800,
        "Time Diff": 4.994
    },
    {
        "Xenobi Ranking": 21
    },
    {
        "Last Updated": "2024-05-07T23:08:17.489037"
    }
]