[
    {
        "Node IP": "185.7.170.xxx",
        "Block ID": 2343386,
        "Time Diff": 1.014
    },
    {
        "Node IP": "37.27.68.xxx",
        "Block ID": 2343386,
        "Time Diff": 1.057
    },
    {
        "Node IP": "144.208.193.xxx",
        "Block ID": 2343386,
        "Time Diff": 1.112
    },
    {
        "Node IP": "178.217.199.xxx",
        "Block ID": 2343386,
        "Time Diff": 1.142
    },
    {
        "Node IP": "189.217.80.xxx",
        "Block ID": 2343386,
        "Time Diff": 1.149
    },
    {
        "Node IP": "97.85.41.xxx",
        "Block ID": 2343386,
        "Time Diff": 1.157
    },
    {
        "Node IP": "78.46.80.xxx",
        "Block ID": 2343386,
        "Time Diff": 1.177
    },
    {
        "Node IP": "37.27.51.xxx",
        "Block ID": 2343386,
        "Time Diff": 1.28
    },
    {
        "Node IP": "65.109.114.xxx",
        "Block ID": 2343386,
        "Time Diff": 1.294
    },
    {
        "Node IP": "162.19.99.xxx",
        "Block ID": 2343386,
        "Time Diff": 1.322
    },
    {
        "Node IP": "66.203.113.xxx",
        "Block ID": 2343386,
        "Time Diff": 1.343
    },
    {
        "Node IP": "73.156.3.xxx",
        "Block ID": 2343386,
        "Time Diff": 1.347
    },
    {
        "Node IP": "79.190.201.xxx",
        "Block ID": 2343386,
        "Time Diff": 1.368
    },
    {
        "Node IP": "188.214.130.xxx",
        "Block ID": 2343386,
        "Time Diff": 1.388
    },
    {
        "Node IP": "144.76.3.xxx",
        "Block ID": 2343386,
        "Time Diff": 1.393
    },
    {
        "Node IP": "98.122.100.xxx",
        "Block ID": 2343386,
        "Time Diff": 1.41
    },
    {
        "Node IP": "27.109.214.xxx",
        "Block ID": 2343386,
        "Time Diff": 1.502
    },
    {
        "Node IP": "160.202.130.xxx",
        "Block ID": 2343386,
        "Time Diff": 1.514
    },
    {
        "Node IP": "176.109.50.xxx",
        "Block ID": 2343386,
        "Time Diff": 1.585
    },
    {
        "Node IP": "74.50.77.xxx",
        "Block ID": 2343386,
        "Time Diff": 1.603
    },
    {
        "Node IP": "61.231.228.xxx",
        "Block ID": 2343386,
        "Time Diff": 1.619
    },
    {
        "Node IP": "161.97.146.xxx",
        "Block ID": 2343386,
        "Time Diff": 1.663
    },
    {
        "Node IP": "74.50.94.xxx",
        "Block ID": 2343386,
        "Time Diff": 1.667
    },
    {
        "Node IP": "98.226.9.xxx",
        "Block ID": 2343386,
        "Time Diff": 1.679
    },
    {
        "Node IP": "177.54.146.xxx",
        "Block ID": 2343386,
        "Time Diff": 1.685
    },
    {
        "Node IP": "83.5.181.xxx",
        "Block ID": 2343386,
        "Time Diff": 1.715
    },
    {
        "Node IP": "64.20.33.xxx",
        "Block ID": 2343386,
        "Time Diff": 1.723
    },
    {
        "Node IP": "74.50.76.xxx",
        "Block ID": 2343386,
        "Time Diff": 1.738
    },
    {
        "Node IP": "185.166.169.xxx",
        "Block ID": 2343386,
        "Time Diff": 1.739
    },
    {
        "Node IP": "135.181.246.xxx",
        "Block ID": 2343386,
        "Time Diff": 1.783
    },
    {
        "Node IP": "159.196.169.xxx",
        "Block ID": 2343386,
        "Time Diff": 1.794
    },
    {
        "Node IP": "109.205.213.xxx",
        "Block ID": 2343386,
        "Time Diff": 1.804
    },
    {
        "Node IP": "162.55.2.xxx",
        "Block ID": 2343386,
        "Time Diff": 1.818
    },
    {
        "Node IP": "43.133.227.xxx",
        "Block ID": 2343386,
        "Time Diff": 1.825
    },
    {
        "Node IP": "67.217.49.xxx",
        "Block ID": 2343386,
        "Time Diff": 1.867
    },
    {
        "Node IP": "135.181.228.xxx",
        "Block ID": 2343386,
        "Time Diff": 1.87
    },
    {
        "Node IP": "65.25.183.xxx",
        "Block ID": 2343386,
        "Time Diff": 1.91
    },
    {
        "Node IP": "188.137.48.xxx",
        "Block ID": 2343386,
        "Time Diff": 1.949
    },
    {
        "Node IP": "64.20.46.xxx",
        "Block ID": 2343386,
        "Time Diff": 1.958
    },
    {
        "Node IP": "66.45.225.xxx",
        "Block ID": 2343386,
        "Time Diff": 1.998
    },
    {
        "Node IP": "213.76.115.xxx",
        "Block ID": 2343386,
        "Time Diff": 2.021
    },
    {
        "Node IP": "213.239.194.xxx",
        "Block ID": 2343386,
        "Time Diff": 2.021
    },
    {
        "Node IP": "116.202.173.xxx",
        "Block ID": 2343386,
        "Time Diff": 2.032
    },
    {
        "Node IP": "43.134.28.xxx",
        "Block ID": 2343386,
        "Time Diff": 2.054
    },
    {
        "Node IP": "69.10.38.xxx",
        "Block ID": 2343386,
        "Time Diff": 2.073
    },
    {
        "Node IP": "129.226.81.xxx",
        "Block ID": 2343386,
        "Time Diff": 2.091
    },
    {
        "Node IP": "173.214.168.xxx",
        "Block ID": 2343386,
        "Time Diff": 2.096
    },
    {
        "Node IP": "139.177.189.xxx",
        "Block ID": 2343386,
        "Time Diff": 2.105
    },
    {
        "Node IP": "84.247.185.xxx",
        "Block ID": 2343386,
        "Time Diff": 2.112
    },
    {
        "Node IP": "161.97.141.xxx",
        "Block ID": 2343386,
        "Time Diff": 2.112
    },
    {
        "Xenobi Ranking": 20
    },
    {
        "Last Updated": "2024-03-29T03:24:46.934105"
    }
]