[
    {
        "Node IP": "37.27.68.xxx",
        "Block ID": 1956122,
        "Time Diff": 5.884
    },
    {
        "Node IP": "97.85.41.xxx",
        "Block ID": 1956122,
        "Time Diff": 6.319
    },
    {
        "Node IP": "113.90.84.xxx",
        "Block ID": 1956122,
        "Time Diff": 6.357
    },
    {
        "Node IP": "189.217.92.xxx",
        "Block ID": 1956122,
        "Time Diff": 6.768
    },
    {
        "Node IP": "162.19.99.xxx",
        "Block ID": 1956122,
        "Time Diff": 6.904
    },
    {
        "Node IP": "79.190.201.xxx",
        "Block ID": 1956122,
        "Time Diff": 7.04
    },
    {
        "Node IP": "58.169.131.xxx",
        "Block ID": 1956122,
        "Time Diff": 7.115
    },
    {
        "Node IP": "84.59.129.xxx",
        "Block ID": 1956122,
        "Time Diff": 7.528
    },
    {
        "Node IP": "96.250.163.xxx",
        "Block ID": 1956122,
        "Time Diff": 7.639
    },
    {
        "Node IP": "27.109.214.xxx",
        "Block ID": 1956122,
        "Time Diff": 7.727
    },
    {
        "Node IP": "73.156.3.xxx",
        "Block ID": 1956122,
        "Time Diff": 7.838
    },
    {
        "Node IP": "129.222.87.xxx",
        "Block ID": 1956122,
        "Time Diff": 7.87
    },
    {
        "Node IP": "178.217.199.xxx",
        "Block ID": 1956122,
        "Time Diff": 7.875
    },
    {
        "Node IP": "98.226.9.xxx",
        "Block ID": 1956122,
        "Time Diff": 8.004
    },
    {
        "Node IP": "176.109.50.xxx",
        "Block ID": 1956122,
        "Time Diff": 8.221
    },
    {
        "Node IP": "74.50.77.xxx",
        "Block ID": 1956122,
        "Time Diff": 8.469
    },
    {
        "Node IP": "61.231.199.xxx",
        "Block ID": 1956122,
        "Time Diff": 8.478
    },
    {
        "Node IP": "188.214.130.xxx",
        "Block ID": 1956122,
        "Time Diff": 8.627
    },
    {
        "Node IP": "135.181.246.xxx",
        "Block ID": 1956122,
        "Time Diff": 8.662
    },
    {
        "Node IP": "71.167.199.xxx",
        "Block ID": 1956122,
        "Time Diff": 8.829
    },
    {
        "Node IP": "74.50.76.xxx",
        "Block ID": 1956122,
        "Time Diff": 8.939
    },
    {
        "Node IP": "83.6.123.xxx",
        "Block ID": 1956122,
        "Time Diff": 8.96
    },
    {
        "Node IP": "144.168.61.xxx",
        "Block ID": 1956122,
        "Time Diff": 9.535
    },
    {
        "Node IP": "65.21.69.xxx",
        "Block ID": 1956122,
        "Time Diff": 9.608
    },
    {
        "Node IP": "185.166.170.xxx",
        "Block ID": 1956122,
        "Time Diff": 9.651
    },
    {
        "Node IP": "160.202.130.xxx",
        "Block ID": 1956122,
        "Time Diff": 10.017
    },
    {
        "Node IP": "144.208.193.xxx",
        "Block ID": 1956122,
        "Time Diff": 10.084
    },
    {
        "Node IP": "65.25.183.xxx",
        "Block ID": 1956122,
        "Time Diff": 10.203
    },
    {
        "Node IP": "103.156.58.xxx",
        "Block ID": 1956122,
        "Time Diff": 10.249
    },
    {
        "Node IP": "213.76.115.xxx",
        "Block ID": 1956122,
        "Time Diff": 10.483
    },
    {
        "Node IP": "93.180.190.xxx",
        "Block ID": 1956122,
        "Time Diff": 10.585
    },
    {
        "Node IP": "43.134.21.xxx",
        "Block ID": 1956122,
        "Time Diff": 10.744
    },
    {
        "Node IP": "98.122.100.xxx",
        "Block ID": 1956122,
        "Time Diff": 10.892
    },
    {
        "Node IP": "64.20.33.xxx",
        "Block ID": 1956122,
        "Time Diff": 10.905
    },
    {
        "Node IP": "43.153.192.xxx",
        "Block ID": 1956122,
        "Time Diff": 11.046
    },
    {
        "Node IP": "119.28.188.xxx",
        "Block ID": 1956122,
        "Time Diff": 11.104
    },
    {
        "Node IP": "64.20.46.xxx",
        "Block ID": 1956122,
        "Time Diff": 11.151
    },
    {
        "Node IP": "207.244.242.xxx",
        "Block ID": 1956122,
        "Time Diff": 11.186
    },
    {
        "Node IP": "103.89.14.xxx",
        "Block ID": 1956122,
        "Time Diff": 11.34
    },
    {
        "Node IP": "154.38.162.xxx",
        "Block ID": 1956122,
        "Time Diff": 11.379
    },
    {
        "Node IP": "43.133.227.xxx",
        "Block ID": 1956122,
        "Time Diff": 11.383
    },
    {
        "Node IP": "37.27.61.xxx",
        "Block ID": 1956122,
        "Time Diff": 11.544
    },
    {
        "Node IP": "129.226.81.xxx",
        "Block ID": 1956122,
        "Time Diff": 11.665
    },
    {
        "Node IP": "43.163.8.xxx",
        "Block ID": 1956122,
        "Time Diff": 11.701
    },
    {
        "Node IP": "45.56.113.xxx",
        "Block ID": 1956122,
        "Time Diff": 11.703
    },
    {
        "Node IP": "116.202.173.xxx",
        "Block ID": 1956122,
        "Time Diff": 11.742
    },
    {
        "Node IP": "185.7.170.xxx",
        "Block ID": 1956122,
        "Time Diff": 11.924
    },
    {
        "Node IP": "43.134.28.xxx",
        "Block ID": 1956122,
        "Time Diff": 12.009
    },
    {
        "Node IP": "92.205.177.xxx",
        "Block ID": 1956122,
        "Time Diff": 12.04
    },
    {
        "Node IP": "113.176.163.xxx",
        "Block ID": 1956122,
        "Time Diff": 12.222
    },
    {
        "Xenobi Ranking": 16
    },
    {
        "Last Updated": "2024-03-12T11:18:01.474512"
    }
]