[
    {
        "Node IP": "185.7.170.xxx",
        "Block ID": 2774322,
        "Time Diff": 1.636
    },
    {
        "Node IP": "162.55.2.xxx",
        "Block ID": 2774322,
        "Time Diff": 1.826
    },
    {
        "Node IP": "188.137.48.xxx",
        "Block ID": 2774322,
        "Time Diff": 2.136
    },
    {
        "Node IP": "79.190.201.xxx",
        "Block ID": 2774322,
        "Time Diff": 2.148
    },
    {
        "Node IP": "37.27.68.xxx",
        "Block ID": 2774322,
        "Time Diff": 2.214
    },
    {
        "Node IP": "109.205.213.xxx",
        "Block ID": 2774322,
        "Time Diff": 2.278
    },
    {
        "Node IP": "96.250.163.xxx",
        "Block ID": 2774322,
        "Time Diff": 2.323
    },
    {
        "Node IP": "162.19.99.xxx",
        "Block ID": 2774322,
        "Time Diff": 2.332
    },
    {
        "Node IP": "144.126.133.xxx",
        "Block ID": 2774322,
        "Time Diff": 2.345
    },
    {
        "Node IP": "65.21.69.xxx",
        "Block ID": 2774322,
        "Time Diff": 2.407
    },
    {
        "Node IP": "67.85.107.xxx",
        "Block ID": 2774322,
        "Time Diff": 2.458
    },
    {
        "Node IP": "97.85.41.xxx",
        "Block ID": 2774322,
        "Time Diff": 2.476
    },
    {
        "Node IP": "176.109.50.xxx",
        "Block ID": 2774322,
        "Time Diff": 2.483
    },
    {
        "Node IP": "74.50.77.xxx",
        "Block ID": 2774322,
        "Time Diff": 2.499
    },
    {
        "Node IP": "58.169.131.xxx",
        "Block ID": 2774322,
        "Time Diff": 2.543
    },
    {
        "Node IP": "69.10.51.xxx",
        "Block ID": 2774322,
        "Time Diff": 2.586
    },
    {
        "Node IP": "89.77.74.xxx",
        "Block ID": 2774322,
        "Time Diff": 2.663
    },
    {
        "Node IP": "57.128.95.xxx",
        "Block ID": 2774322,
        "Time Diff": 2.68
    },
    {
        "Node IP": "135.181.246.xxx",
        "Block ID": 2774322,
        "Time Diff": 2.682
    },
    {
        "Node IP": "198.84.243.xxx",
        "Block ID": 2774322,
        "Time Diff": 2.693
    },
    {
        "Node IP": "188.214.130.xxx",
        "Block ID": 2774322,
        "Time Diff": 2.714
    },
    {
        "Node IP": "135.181.238.xxx",
        "Block ID": 2774322,
        "Time Diff": 2.715
    },
    {
        "Node IP": "74.50.76.xxx",
        "Block ID": 2774322,
        "Time Diff": 2.737
    },
    {
        "Node IP": "162.250.127.xxx",
        "Block ID": 2774322,
        "Time Diff": 2.742
    },
    {
        "Node IP": "161.97.146.xxx",
        "Block ID": 2774322,
        "Time Diff": 2.764
    },
    {
        "Node IP": "27.109.214.xxx",
        "Block ID": 2774322,
        "Time Diff": 2.767
    },
    {
        "Node IP": "67.217.54.xxx",
        "Block ID": 2774322,
        "Time Diff": 2.828
    },
    {
        "Node IP": "34.174.159.xxx",
        "Block ID": 2774322,
        "Time Diff": 2.859
    },
    {
        "Node IP": "37.27.51.xxx",
        "Block ID": 2774322,
        "Time Diff": 2.868
    },
    {
        "Node IP": "161.97.141.xxx",
        "Block ID": 2774322,
        "Time Diff": 2.923
    },
    {
        "Node IP": "74.50.94.xxx",
        "Block ID": 2774322,
        "Time Diff": 2.964
    },
    {
        "Node IP": "135.181.228.xxx",
        "Block ID": 2774322,
        "Time Diff": 3.034
    },
    {
        "Node IP": "199.66.65.xxx",
        "Block ID": 2774322,
        "Time Diff": 3.077
    },
    {
        "Node IP": "69.10.38.xxx",
        "Block ID": 2774322,
        "Time Diff": 3.16
    },
    {
        "Node IP": "85.10.195.xxx",
        "Block ID": 2774322,
        "Time Diff": 3.168
    },
    {
        "Node IP": "144.168.61.xxx",
        "Block ID": 2774322,
        "Time Diff": 3.183
    },
    {
        "Node IP": "65.25.183.xxx",
        "Block ID": 2774322,
        "Time Diff": 3.233
    },
    {
        "Node IP": "83.5.151.xxx",
        "Block ID": 2774322,
        "Time Diff": 3.258
    },
    {
        "Node IP": "89.64.42.xxx",
        "Block ID": 2774322,
        "Time Diff": 3.29
    },
    {
        "Node IP": "149.102.156.xxx",
        "Block ID": 2774322,
        "Time Diff": 3.306
    },
    {
        "Node IP": "173.214.168.xxx",
        "Block ID": 2774322,
        "Time Diff": 3.31
    },
    {
        "Node IP": "159.196.169.xxx",
        "Block ID": 2774322,
        "Time Diff": 3.372
    },
    {
        "Node IP": "74.50.78.xxx",
        "Block ID": 2774322,
        "Time Diff": 3.421
    },
    {
        "Node IP": "98.122.100.xxx",
        "Block ID": 2774322,
        "Time Diff": 3.461
    },
    {
        "Node IP": "77.253.146.xxx",
        "Block ID": 2774322,
        "Time Diff": 3.493
    },
    {
        "Node IP": "1.162.241.xxx",
        "Block ID": 2774322,
        "Time Diff": 3.504
    },
    {
        "Node IP": "66.45.225.xxx",
        "Block ID": 2774322,
        "Time Diff": 3.592
    },
    {
        "Node IP": "205.209.117.xxx",
        "Block ID": 2774322,
        "Time Diff": 3.601
    },
    {
        "Node IP": "71.167.199.xxx",
        "Block ID": 2774322,
        "Time Diff": 3.717
    },
    {
        "Node IP": "113.247.111.xxx",
        "Block ID": 2774322,
        "Time Diff": 3.793
    },
    {
        "Xenobi Ranking": 14
    },
    {
        "Last Updated": "2024-04-11T07:20:22.445386"
    }
]